Metadata-Version: 1.0
Name: koboripackage
Version: 1.0
Summary: Pythonのディレクトリ構成のテスト用
Home-page: https://github.com/koboriakira/python_package
Author: Kobori Akira
Author-email: private.beats@gmail.com
License: UNKNOWN
Platform: UNKNOWN
